graia/component/__init__.py
graia_component_selector-0.0.6.dist-info/WHEEL
graia_component_selector-0.0.6.dist-info/METADATA
graia_component_selector-0.0.6.dist-info/RECORD
