Metadata-Version: 2.1
Name: graia-component-selector
Version: 0.0.6
Summary: 
License: MIT
Author: GreyElaina
Author-email: GreyElaina@outlook.com
Requires-Python: >=3.7,<4.0
Classifier: License :: OSI Approved :: MIT License
Classifier: Programming Language :: Python :: 3
Classifier: Programming Language :: Python :: 3.7
Classifier: Programming Language :: Python :: 3.8
Classifier: Programming Language :: Python :: 3.9
Requires-Dist: graia-application-mirai
Requires-Dist: graia-broadcast (>=0.7.0)
